swarmauri_mre_crypto_pgp/PGPSealMreCrypto.py
swarmauri_mre_crypto_pgp/__init__.py
swarmauri_mre_crypto_pgp/pgp_mre.py
swarmauri_mre_crypto_pgp/pgp_sealed_cek_mre.py
swarmauri_mre_crypto_pgp-0.3.0.dev4.dist-info/LICENSE
swarmauri_mre_crypto_pgp-0.3.0.dev4.dist-info/METADATA
swarmauri_mre_crypto_pgp-0.3.0.dev4.dist-info/WHEEL
swarmauri_mre_crypto_pgp-0.3.0.dev4.dist-info/entry_points.txt
swarmauri_mre_crypto_pgp-0.3.0.dev4.dist-info/RECORD
